setup.py
skywise_historical_obs.egg-info/PKG-INFO
skywise_historical_obs.egg-info/SOURCES.txt
skywise_historical_obs.egg-info/dependency_links.txt
skywise_historical_obs.egg-info/not-zip-safe
skywise_historical_obs.egg-info/requires.txt
skywise_historical_obs.egg-info/top_level.txt
skywisehistoricalobs/__init__.py
skywisehistoricalobs/observation.py
skywisehistoricalobs/station.py