Metadata-Version: 1.1
Name: skywise-historical-obs
Version: 0.1.3
Summary: SkyWise Historical Obs Python Client Library
Home-page: UNKNOWN
Author: Weather Decision Technologies
Author-email: support@wdtinc.com
License: UNKNOWN
Platform: UNKNOWN
Classifier: Development Status :: 3 - Alpha
Classifier: Intended Audience :: Developers
Classifier: Natural Language :: English
Classifier: Programming Language :: Python
Classifier: Programming Language :: Python :: 2.7
